{
    "name": "scene",
    "objects": [
        {
            "type": "LIGHT",
            "name": "Light",
            "transform": {
                "translation": [
                    4.076245307922363,
                    1.0054539442062378,
                    5.903861999511719
                ],
                "rotation": [
                    9.68732738494873,
                    15.594269752502441,
                    43.30875015258789
                ],
                "scaling": [
                    1.0,
                    0.9999999403953552,
                    1.0
                ]
            }
        },
        {
            "type": "CAMERA",
            "name": "Camera",
            "transform": {
                "translation": [
                    0.0,
                    -80.0,
                    30.0
                ],
                "rotation": [
                    40.51423645019531,
                    0.0,
                    0.0
                ],
                "scaling": [
                    1.0,
                    1.0,
                    1.0
                ]
            }
        },
        {
            "type": "MESH",
            "name": "Ground",
            "transform": {
                "translation": [
                    0.0,
                    0.0,
                    -2.0
                ],
                "rotation": [
                    0.0,
                    0.0,
                    0.0
                ],
                "scaling": [
                    100.0,
                    100.0,
                    2.0
                ]
            },
            "file_name": "Ground"
        },
        {
            "type": "MESH",
            "name": "Player",
            "transform": {
                "translation": [
                    0.0,
                    -20.0,
                    2.0
                ],
                "rotation": [
                    0.0,
                    0.0,
                    0.0
                ],
                "scaling": [
                    1.0,
                    1.0,
                    1.0
                ]
            },
            "file_name": "Player",
            "collider": {
                "type": "BOX",
                "center": [
                    0.0,
                    0.0,
                    0.0
                ],
                "size": [
                    2.0,
                    2.0,
                    4.0
                ]
            }
        },
        {
            "type": "MESH",
            "name": "Enemy",
            "transform": {
                "translation": [
                    0.0,
                    0.0,
                    4.0
                ],
                "rotation": [
                    0.0,
                    0.0,
                    0.0
                ],
                "scaling": [
                    1.0,
                    1.0,
                    1.0
                ]
            },
            "file_name": "Enemy",
            "collider": {
                "type": "BOX",
                "center": [
                    0.0,
                    0.0,
                    0.0
                ],
                "size": [
                    8.0,
                    8.0,
                    8.0
                ]
            }
        }
    ]
}